linkedin_scraper_db/__init__.py
linkedin_scraper_db/clean_html.py
linkedin_scraper_db/excel_db.py
linkedin_scraper_db/helper.py
linkedin_scraper_db/keys.py
linkedin_scraper_db/main.py
linkedin_scraper_db/prompt.py
linkedin_scraper_db/structure_html.py
linkedin_scraper_db-1.0.0.dist-info/METADATA
linkedin_scraper_db-1.0.0.dist-info/WHEEL
linkedin_scraper_db-1.0.0.dist-info/top_level.txt
linkedin_scraper_db-1.0.0.dist-info/RECORD
