Metadata-Version: 2.1
Name: linkedin-scraper-db
Version: 1.0.0
Summary: Scrapes multiple profiles on Linkedin
Home-page: https://github.com/wcisco17/linkedin_scraper_db
Author: Williams Sissoko
Author-email: 
License: UNKNOWN
Download-URL: https://github.com/wcisco17/linkedin_scraper_db/dist/1.0.0.tar.gz
Keywords: linkedin,scraping,scraper,multiple linkedin profiles
Platform: UNKNOWN
Requires-Dist: selenium
Requires-Dist: parsel
Requires-Dist: setuptools
